Workbook

Sheet Project Information
A1: PROJECT INFORMATION
A3: Project Name | B3: ParaBank QA Testing
A4: Application Name | B4: ParaBank (Parasoft demo banking application)
A5: Application URL | B5: https://parabank.parasoft.com/parabank/index.htm
A6: Application Type | B6: Web Application
A7: Document Type | B7: QA Test Documentation
A8: Version | B8: 1.0
A9: Prepared By | B9: Ghanshyam Sharma
A10: Testing Approach | B10: Manual Testing
A11: Environment | B11: ParaBank Demo
A12: Browser | B12: Chrome
A13: Operating System | B13: Windows
A14: Date | B14: 46257
A16: Documentation Index
A17: Sheet | B17: Purpose
A18: Project Information | B18: Project and testing information
A19: Test-Scenario | B19: Master list of test scenarios
A20: Test Cases | B20: Detailed test cases mapped to scenarios
A21: RTM | B21: Requirement-to-test-case mapping with execution summary
A22: Defects | B22: Defects identified during testing
A24: Notes and Assumptions
A25: • Test data for Registration, Login, Update Contact Info etc. was provided by the tester (Ghanshyam Sharma); remaining data was chosen by the tester's instruction.
A26: • ParaBank has no formal FRS, so requirements in the RTM are derived from the application's visible functionality.
A27: • Expected results describe the correct behaviour of the feature. Exact message wording must be confirmed during execution.
A28: • ParaBank demo data can be reset by Parasoft. If user ghanshyam18n no longer exists, register again (backup username: ghanshyam18n01).

Sheet Test-Scenario
A1: Project Name | B1: ParaBank (Front-End)
A2: Client | B2: Parasoft (ParaBank demo)
A3: Created By | B3: Ghanshyam Sharma
A4: Creation Date | B4: 46318
A5: Approval Date
A7: Test Scenario ID | B7: Module | C7: Reference | D7: Test Scenario | E7: Priority | F7: Number of Test Cases
A8: TS_01 | B8: Register | C8: FRS | D8: Verify the working of Registration functionality on ParaBank. | E8: P0 | F8: =COUNTIF('Test Cases'!$B$6:$B$500,A8&"*") -> 10
A9: TS_02 | B9: Login | C9: FRS | D9: Validate the working of Login functionality on ParaBank. | E9: P0 | F9: =COUNTIF('Test Cases'!$B$6:$B$500,A9&"*") -> 9
A10: TS_03 | B10: Login | C10: FRS | D10: Validate the working of Logout functionality on ParaBank. | E10: P0 | F10: =COUNTIF('Test Cases'!$B$6:$B$500,A10&"*") -> 3
A11: TS_04 | B11: Login | C11: FRS | D11: Validate the working of Forgot Login Info (Customer Lookup) functionality. | E11: P2 | F11: =COUNTIF('Test Cases'!$B$6:$B$500,A11&"*") -> 4
A12: TS_05 | B12: Open New Account | C12: FRS | D12: Verify the working of Open New Account functionality. | E12: P0 | F12: =COUNTIF('Test Cases'!$B$6:$B$500,A12&"*") -> 7
A13: TS_06 | B13: Accounts Overview | C13: FRS | D13: Verify the working of Accounts Overview functionality. | E13: P0 | F13: =COUNTIF('Test Cases'!$B$6:$B$500,A13&"*") -> 5
A14: TS_07 | B14: Accounts Overview | C14: FRS | D14: Verify the working of Account Details and Account Activity functionality. | E14: P1 | F14: =COUNTIF('Test Cases'!$B$6:$B$500,A14&"*") -> 5
A15: TS_08 | B15: Transfer Funds | C15: FRS | D15: Verify the working of Transfer Funds functionality. | E15: P0 | F15: =COUNTIF('Test Cases'!$B$6:$B$500,A15&"*") -> 11
A16: TS_09 | B16: Bill Pay | C16: FRS | D16: Verify the working of Bill Pay functionality. | E16: P0 | F16: =COUNTIF('Test Cases'!$B$6:$B$500,A16&"*") -> 11
A17: TS_10 | B17: Find Transactions | C17: FRS | D17: Verify the working of Find Transactions functionality. | E17: P1 | F17: =COUNTIF('Test Cases'!$B$6:$B$500,A17&"*") -> 8
A18: TS_11 | B18: Update Contact Info | C18: FRS | D18: Verify the working of Update Contact Info functionality. | E18: P1 | F18: =COUNTIF('Test Cases'!$B$6:$B$500,A18&"*") -> 6
A19: TS_12 | B19: Request Loan | C19: FRS | D19: Verify the working of Request Loan functionality. | E19: P1 | F19: =COUNTIF('Test Cases'!$B$6:$B$500,A19&"*") -> 8
E20: Total | F20: =SUM(F8:F19) -> 87

Sheet Test Cases
A1: Client Name | B1: Parasoft (ParaBank demo)
A2: Prepared By | B2: Ghanshyam Sharma
A3: Version Number | B3: Version 1.0
A5: Test Case ID | B5: Test Scenario | C5: Test Case Title | D5: Pre-Condition | E5: Test Step | F5: Test Data | G5: Expected Result | H5: Actual Result | I5: Priority | J5: Result
A6: TC-RF-01 | B6: TS_01 - Register Functionality | C6: Verify registration with all valid data | D6: ParaBank home page is open in Chrome (https://parabank.parasoft.com/parabank/index.htm) | E6: 1. Click 'Register' link on the login panel 2. Enter all the fields with valid data 3. Click 'Register' button | F6: First Name: Ghanshyam Last Name: Sharma Address: Punjagutta City: Hyderabad State: Telangana Zip Code: 500078 Phone: 1234567897 SSN: 987-65-4321 Username: ghanshyam18n Password: 123@cseIT Confirm: 123@cseIT | G6: Account is created. Welcome message with username 'ghanshyam18n' is shown and user is logged in automatically. | I6: P0 | J6: Not Executed
A7: TC-RF-02 | B7: TS_01 - Register Functionality | C7: Verify all fields and buttons are displayed on Register page | D7: ParaBank home page is open in Chrome (https://parabank.parasoft.com/parabank/index.htm) | E7: 1. Click 'Register' link 2. Check the form labels and button | F7: N/A | G7: Fields First Name, Last Name, Address, City, State, Zip Code, Phone #, SSN, Username, Password, Confirm and 'Register' button are displayed. | I7: P2 | J7: Not Executed
A8: TC-RF-03 | B8: TS_01 - Register Functionality | C8: Verify registration with all fields blank | D8: Register page is open | E8: 1. Leave all fields empty 2. Click 'Register' button | F8: All fields blank | G8: Account is not created. A 'required' error message is shown for each mandatory field. | I8: P1 | J8: Not Executed
A9: TC-RF-04 | B9: TS_01 - Register Functionality | C9: Verify registration with SSN blank | D9: Register page is open | E9: 1. Fill all fields except SSN 2. Click 'Register' button | F9: First Name: Ghanshyam Last Name: Sharma Address: Punjagutta City: Hyderabad State: Telangana Zip Code: 500078 Phone: 1234567897 SSN: (blank) Username: ghanshyam18n Password: 123@cseIT Confirm: 123@cseIT | G9: Account is not created. 'Social Security Number is required' error is shown. | I9: P1 | J9: Not Executed
A10: TC-RF-05 | B10: TS_01 - Register Functionality | C10: Verify registration with Username blank | D10: Register page is open | E10: 1. Fill all fields except Username 2. Click 'Register' button | F10: First Name: Ghanshyam Last Name: Sharma Address: Punjagutta City: Hyderabad State: Telangana Zip Code: 500078 Phone: 1234567897 SSN: 987-65-4321 Username: (blank) Password: 123@cseIT Confirm: 123@cseIT | G10: Account is not created. 'Username is required' error is shown. | I10: P1 | J10: Not Executed
A11: TC-RF-06 | B11: TS_01 - Register Functionality | C11: Verify registration with Password and Confirm Password blank | D11: Register page is open | E11: 1. Fill all fields except Password and Confirm 2. Click 'Register' button | F11: First Name: Ghanshyam Last Name: Sharma Address: Punjagutta City: Hyderabad State: Telangana Zip Code: 500078 Phone: 1234567897 SSN: 987-65-4321 Username: ghanshyam18n Password: (blank) Confirm: (blank) | G11: Account is not created. Password and password confirmation required errors are shown. | I11: P1 | J11: Not Executed
A12: TC-RF-07 | B12: TS_01 - Register Functionality | C12: Verify registration when Confirm Password does not match Password | D12: Register page is open | E12: 1. Fill all fields 2. Enter a different value in Confirm field 3. Click 'Register' button | F12: First Name: Ghanshyam Last Name: Sharma Address: Punjagutta City: Hyderabad State: Telangana Zip Code: 500078 Phone: 1234567897 SSN: 987-65-4321 Username: ghanshyam18n Password: 123@cseIT Confirm: 123@cseIT1 | G12: Account is not created. 'Passwords did not match' error is shown. | I12: P0 | J12: Not Executed
A13: TC-RF-08 | B13: TS_01 - Register Functionality | C13: Verify registration with an already existing username | D13: User ghanshyam18n is already registered; user is logged out | E13: 1. Click 'Register' 2. Fill all fields using username ghanshyam18n 3. Click 'Register' button | F13: First Name: Ghanshyam Last Name: Sharma Address: Punjagutta City: Hyderabad State: Telangana Zip Code: 500078 Phone: 1234567897 SSN: 987-65-4321 Username: ghanshyam18n Password: 123@cseIT Confirm: 123@cseIT | G13: Account is not created. 'This username already exists' error is shown. | I13: P0 | J13: Not Executed
A14: TC-RF-09 | B14: TS_01 - Register Functionality | C14: Verify registration with Phone number left blank | D14: Register page is open | E14: 1. Fill all fields except Phone # 2. Click 'Register' button | F14: First Name: Ghanshyam Last Name: Sharma Address: Punjagutta City: Hyderabad State: Telangana Zip Code: 500078 Phone: (blank) SSN: 987-65-4321 Username: ghanshyam18n02 Password: 123@cseIT Confirm: 123@cseIT | G14: Phone # is optional, so the account is created successfully (verify against actual behaviour). | I14: P3 | J14: Not Executed
A15: TC-RF-10 | B15: TS_01 - Register Functionality | C15: Verify registration with alphabets in Zip Code and Phone fields | D15: Register page is open | E15: 1. Enter Zip Code and Phone with alphabets 2. Fill other fields with valid data 3. Click 'Register' button | F15: First Name: Ghanshyam Last Name: Sharma Address: Punjagutta City: Hyderabad State: Telangana Zip Code: ABCDE Phone: abcdefghij SSN: 987-65-4321 Username: ghanshyam18n03 Password: 123@cseIT Confirm: 123@cseIT | G15: Account should not be created; a validation message for invalid Zip Code / Phone is expected. | I15: P2 | J15: Not Executed
A16: TC-LF-01 | B16: TS_02 - Login Functionality | C16: Verify login with valid username and password | D16: ParaBank home page is open in Chrome (https://parabank.parasoft.com/parabank/index.htm) | E16: 1. Enter valid username and password in the login panel 2. Click 'Log In' button | F16: Username: ghanshyam18n Password: 123@cseIT | G16: User is logged in and the Accounts Overview page is displayed. | I16: P0 | J16: Not Executed
A17: TC-LF-02 | B17: TS_02 - Login Functionality | C17: Verify login with valid username and wrong password | D17: ParaBank home page is open in Chrome (https://parabank.parasoft.com/parabank/index.htm) | E17: 1. Enter valid username and wrong password 2. Click 'Log In' | F17: Username: ghanshyam18n Password: wrongPass@1 | G17: Login fails. 'The username and password could not be verified' error is shown. | I17: P0 | J17: Not Executed
... A92: TC-RL-08 | B92: TS_12 - Request Loan Functionality | C92: Verify loan request with alphabets in loan amount | D92: User ghanshyam18n is registered and logged in to ParaBank | E92: 1. Enter alphabets in Loan Amount 2. Click 'Apply Now' | F92: Loan Amount: abc Down Payment: 500 | G92: Loan request is not processed; invalid amount error is shown. | I92: P2 | J92: Not Executed

Sheet RTM
A1: REQUIREMENT TRACEABILITY MATRIX (RTM)
A4: Requirement ID | B4: Requirement Description | C4: Module | D4: Test Scenario ID | E4: Test Case IDs | F4: Total | G4: Pass | H4: Fail | I4: Blocked | J4: Not Executed
A5: FR_01 | B5: A new customer can register with personal details, username and password. | C5: Register | D5: TS_01 | E5: TC-RF-01 to TC-RF-10 | F5: =COUNTIF('Test Cases'!$B$6:$B$500,D5&"*") -> 10 | G5: =COUNTIFS('Test Cases'!$B$6:$B$500,D5&"*",'Test Cases'!$J$6:$J$500,"Pass") -> 0 | H5: =COUNTIFS('Test Cases'!$B$6:$B$500,D5&"*",'Test Cases'!$J$6:$J$500,"Fail") -> 0 | I5: =COUNTIFS('Test Cases'!$B$6:$B$500,D5&"*",'Test Cases'!$J$6:$J$500,"Blocked") -> 0 | J5: =COUNTIFS('Test Cases'!$B$6:$B$500,D5&"*",'Test Cases'!$J$6:$J$500,"Not Executed") -> 10
A6: FR_02 | B6: A registered customer can log in with valid credentials and is blocked with invalid ones. | C6: Login | D6: TS_02 | E6: TC-LF-01 to TC-LF-09 | F6: =COUNTIF('Test Cases'!$B$6:$B$500,D6&"*") -> 9 | G6: =COUNTIFS('Test Cases'!$B$6:$B$500,D6&"*",'Test Cases'!$J$6:$J$500,"Pass") -> 0 | H6: =COUNTIFS('Test Cases'!$B$6:$B$500,D6&"*",'Test Cases'!$J$6:$J$500,"Fail") -> 0 | I6: =COUNTIFS('Test Cases'!$B$6:$B$500,D6&"*",'Test Cases'!$J$6:$J$500,"Blocked") -> 0 | J6: =COUNTIFS('Test Cases'!$B$6:$B$500,D6&"*",'Test Cases'!$J$6:$J$500,"Not Executed") -> 9
A7: FR_03 | B7: A logged-in customer can log out and protected pages are no longer accessible. | C7: Login | D7: TS_03 | E7: TC-LO-01 to TC-LO-03 | F7: =COUNTIF('Test Cases'!$B$6:$B$500,D7&"*") -> 3 | G7: =COUNTIFS('Test Cases'!$B$6:$B$500,D7&"*",'Test Cases'!$J$6:$J$500,"Pass") -> 0 | H7: =COUNTIFS('Test Cases'!$B$6:$B$500,D7&"*",'Test Cases'!$J$6:$J$500,"Fail") -> 0 | I7: =COUNTIFS('Test Cases'!$B$6:$B$500,D7&"*",'Test Cases'!$J$6:$J$500,"Blocked") -> 0 | J7: =COUNTIFS('Test Cases'!$B$6:$B$500,D7&"*",'Test Cases'!$J$6:$J$500,"Not Executed") -> 3
A8: FR_04 | B8: A customer can retrieve login information using personal details. | C8: Login | D8: TS_04 | E8: TC-FL-01 to TC-FL-04 | F8: =COUNTIF('Test Cases'!$B$6:$B$500,D8&"*") -> 4 | G8: =COUNTIFS('Test Cases'!$B$6:$B$500,D8&"*",'Test Cases'!$J$6:$J$500,"Pass") -> 0 | H8: =COUNTIFS('Test Cases'!$B$6:$B$500,D8&"*",'Test Cases'!$J$6:$J$500,"Fail") -> 0 | I8: =COUNTIFS('Test Cases'!$B$6:$B$500,D8&"*",'Test Cases'!$J$6:$J$500,"Blocked") -> 0 | J8: =COUNTIFS('Test Cases'!$B$6:$B$500,D8&"*",'Test Cases'!$J$6:$J$500,"Not Executed") -> 4
A9: FR_05 | B9: A customer can open a new Checking or Savings account from an existing account. | C9: Open New Account | D9: TS_05 | E9: TC-ON-01 to TC-ON-07 | F9: =COUNTIF('Test Cases'!$B$6:$B$500,D9&"*") -> 7 | G9: =COUNTIFS('Test Cases'!$B$6:$B$500,D9&"*",'Test Cases'!$J$6:$J$500,"Pass") -> 0 | H9: =COUNTIFS('Test Cases'!$B$6:$B$500,D9&"*",'Test Cases'!$J$6:$J$500,"Fail") -> 0 | I9: =COUNTIFS('Test Cases'!$B$6:$B$500,D9&"*",'Test Cases'!$J$6:$J$500,"Blocked") -> 0 | J9: =COUNTIFS('Test Cases'!$B$6:$B$500,D9&"*",'Test Cases'!$J$6:$J$500,"Not Executed") -> 7
A10: FR_06 | B10: A customer can view all accounts with balance and available amount. | C10: Accounts Overview | D10: TS_06 | E10: TC-AO-01 to TC-AO-05 | F10: =COUNTIF('Test Cases'!$B$6:$B$500,D10&"*") -> 5 | G10: =COUNTIFS('Test Cases'!$B$6:$B$500,D10&"*",'Test Cases'!$J$6:$J$500,"Pass") -> 0 | H10: =COUNTIFS('Test Cases'!$B$6:$B$500,D10&"*",'Test Cases'!$J$6:$J$500,"Fail") -> 0 | I10: =COUNTIFS('Test Cases'!$B$6:$B$500,D10&"*",'Test Cases'!$J$6:$J$500,"Blocked") -> 0 | J10: =COUNTIFS('Test Cases'!$B$6:$B$500,D10&"*",'Test Cases'!$J$6:$J$500,"Not Executed") -> 5
A11: FR_07 | B11: A customer can view account details and filter account activity. | C11: Accounts Overview | D11: TS_07 | E11: TC-AA-01 to TC-AA-05 | F11: =COUNTIF('Test Cases'!$B$6:$B$500,D11&"*") -> 5 | G11: =COUNTIFS('Test Cases'!$B$6:$B$500,D11&"*",'Test Cases'!$J$6:$J$500,"Pass") -> 0 | H11: =COUNTIFS('Test Cases'!$B$6:$B$500,D11&"*",'Test Cases'!$J$6:$J$500,"Fail") -> 0 | I11: =COUNTIFS('Test Cases'!$B$6:$B$500,D11&"*",'Test Cases'!$J$6:$J$500,"Blocked") -> 0 | J11: =COUNTIFS('Test Cases'!$B$6:$B$500,D11&"*",'Test Cases'!$J$6:$J$500,"Not Executed") -> 5
A12: FR_08 | B12: A customer can transfer funds between own accounts with amount validation. | C12: Transfer Funds | D12: TS_08 | E12: TC-TF-01 to TC-TF-11 | F12: =COUNTIF('Test Cases'!$B$6:$B$500,D12&"*") -> 11 | G12: =COUNTIFS('Test Cases'!$B$6:$B$500,D12&"*",'Test Cases'!$J$6:$J$500,"Pass") -> 0 | H12: =COUNTIFS('Test Cases'!$B$6:$B$500,D12&"*",'Test Cases'!$J$6:$J$500,"Fail") -> 0 | I12: =COUNTIFS('Test Cases'!$B$6:$B$500,D12&"*",'Test Cases'!$J$6:$J$500,"Blocked") -> 0 | J12: =COUNTIFS('Test Cases'!$B$6:$B$500,D12&"*",'Test Cases'!$J$6:$J$500,"Not Executed") -> 11
A13: FR_09 | B13: A customer can pay bills to a payee from an account with proper validation. | C13: Bill Pay | D13: TS_09 | E13: TC-BP-01 to TC-BP-11 | F13: =COUNTIF('Test Cases'!$B$6:$B$500,D13&"*") -> 11 | G13: =COUNTIFS('Test Cases'!$B$6:$B$500,D13&"*",'Test Cases'!$J$6:$J$500,"Pass") -> 0 | H13: =COUNTIFS('Test Cases'!$B$6:$B$500,D13&"*",'Test Cases'!$J$6:$J$500,"Fail") -> 0 | I13: =COUNTIFS('Test Cases'!$B$6:$B$500,D13&"*",'Test Cases'!$J$6:$J$500,"Blocked") -> 0 | J13: =COUNTIFS('Test Cases'!$B$6:$B$500,D13&"*",'Test Cases'!$J$6:$J$500,"Not Executed") -> 11
A14: FR_10 | B14: A customer can search transactions by ID, date, date range and amount. | C14: Find Transactions | D14: TS_10 | E14: TC-FT-01 to TC-FT-08 | F14: =COUNTIF('Test Cases'!$B$6:$B$500,D14&"*") -> 8 | G14: =COUNTIFS('Test Cases'!$B$6:$B$500,D14&"*",'Test Cases'!$J$6:$J$500,"Pass") -> 0 | H14: =COUNTIFS('Test Cases'!$B$6:$B$500,D14&"*",'Test Cases'!$J$6:$J$500,"Fail") -> 0 | I14: =COUNTIFS('Test Cases'!$B$6:$B$500,D14&"*",'Test Cases'!$J$6:$J$500,"Blocked") -> 0 | J14: =COUNTIFS('Test Cases'!$B$6:$B$500,D14&"*",'Test Cases'!$J$6:$J$500,"Not Executed") -> 8
A15: FR_11 | B15: A customer can update address, zip code and phone number. | C15: Update Contact Info | D15: TS_11 | E15: TC-CI-01 to TC-CI-06 | F15: =COUNTIF('Test Cases'!$B$6:$B$500,D15&"*") -> 6 | G15: =COUNTIFS('Test Cases'!$B$6:$B$500,D15&"*",'Test Cases'!$J$6:$J$500,"Pass") -> 0 | H15: =COUNTIFS('Test Cases'!$B$6:$B$500,D15&"*",'Test Cases'!$J$6:$J$500,"Fail") -> 0 | I15: =COUNTIFS('Test Cases'!$B$6:$B$500,D15&"*",'Test Cases'!$J$6:$J$500,"Blocked") -> 0 | J15: =COUNTIFS('Test Cases'!$B$6:$B$500,D15&"*",'Test Cases'!$J$6:$J$500,"Not Executed") -> 6
A16: FR_12 | B16: A customer can request a loan with a down payment and get approved or denied status. | C16: Request Loan | D16: TS_12 | E16: TC-RL-01 to TC-RL-08 | F16: =COUNTIF('Test Cases'!$B$6:$B$500,D16&"*") -> 8 | G16: =COUNTIFS('Test Cases'!$B$6:$B$500,D16&"*",'Test Cases'!$J$6:$J$500,"Pass") -> 0 | H16: =COUNTIFS('Test Cases'!$B$6:$B$500,D16&"*",'Test Cases'!$J$6:$J$500,"Fail") -> 0 | I16: =COUNTIFS('Test Cases'!$B$6:$B$500,D16&"*",'Test Cases'!$J$6:$J$500,"Blocked") -> 0 | J16: =COUNTIFS('Test Cases'!$B$6:$B$500,D16&"*",'Test Cases'!$J$6:$J$500,"Not Executed") -> 8
E17: Total | F17: =SUM(F5:F16) -> 87 | G17: =SUM(G5:G16) -> 0 | H17: =SUM(H5:H16) -> 0 | I17: =SUM(I5:I16) -> 0 | J17: =SUM(J5:J16) -> 87

Sheet Defects
A1: DEFECT LOG
A4: Defect ID | B4: Test Case ID | C4: Module | D4: Defect Summary | E4: Steps to Reproduce | F4: Expected Result | G4: Actual Result | H4: Severity | I4: Priority | J4: Status | K4: Reported By | L4: Reported Date
A5: DEF_01 (sample) | B5: TC-RF-10 | C5: Register | D5: Registration accepts alphabets in Zip Code | E5: 1. Open Register page 2. Enter ABCDE in Zip Code 3. Fill other fields 4. Click Register | F5: Validation message for invalid Zip Code | G5: Account created without any validation | H5: Medium | I5: P2 | J5: New | K5: Ghanshyam Sharma | L5: 46259
